Metadata-Version: 1.0
Name: pmuiprobability
Version: 0.1
Summary: Convenient probability distributions
Home-page: UNKNOWN
Author: Phil Mui
Author-email: thephilmui@gmail.com
License: UNKNOWN
Platform: UNKNOWN
